pydanticai_ollama/__init__.py
pydanticai_ollama/models/__init__.py
pydanticai_ollama/models/ollama.py
pydanticai_ollama/providers/__init__.py
pydanticai_ollama/providers/ollama.py
pydanticai_ollama/settings/__init__.py
pydanticai_ollama/settings/ollama.py
pydanticai_ollama-0.1.4.dist-info/WHEEL
pydanticai_ollama-0.1.4.dist-info/METADATA
pydanticai_ollama-0.1.4.dist-info/RECORD
