Metadata-Version: 2.4
Name: pydanticai-ollama
Version: 0.1.4
Summary: Pydantic AI Ollama integration
Author: ariel-ml
Author-email: ariel-ml <ariel.ai.ml.dl@gmail.com>
License-Expression: MIT
Classifier: Development Status :: 4 - Beta
Classifier: Programming Language :: Python
Classifier: Programming Language :: Python :: 3
Classifier: Programming Language :: Python :: 3 :: Only
Classifier: Programming Language :: Python :: 3.9
Classifier: Programming Language :: Python :: 3.10
Classifier: Programming Language :: Python :: 3.11
Classifier: Programming Language :: Python :: 3.12
Classifier: Programming Language :: Python :: 3.13
Classifier: Intended Audience :: Developers
Classifier: Intended Audience :: Information Technology
Classifier: License :: OSI Approved :: MIT License
Classifier: Operating System :: OS Independent
Classifier: Topic :: Internet
Classifier: Topic :: Scientific/Engineering :: Artificial Intelligence
Classifier: Topic :: Software Development :: Libraries :: Python Modules
Classifier: Framework :: Pydantic
Classifier: Framework :: Pydantic :: 2
Requires-Dist: ollama>=0.5.3
Requires-Dist: pydantic-ai-slim>=1.0.1
Requires-Python: >=3.10
Project-URL: Changelog, https://github.com/ariel-ml/pydanticai-ollama/releases
Project-URL: Documentation, https://github.com/ariel-ml/pydanticai-ollama
Project-URL: Homepage, https://github.com/ariel-ml/pydanticai-ollama
Project-URL: Source, https://github.com/ariel-ml/pydanticai-ollama
